tests/__init__.py
tests/test_core.py
tools4all/__init__.py
tools4all/core.py
tools4all/llm_parser.py
tools4all-0.2.4.dist-info/licenses/LICENSE
tools4all-0.2.4.dist-info/METADATA
tools4all-0.2.4.dist-info/WHEEL
tools4all-0.2.4.dist-info/entry_points.txt
tools4all-0.2.4.dist-info/top_level.txt
tools4all-0.2.4.dist-info/RECORD
