Metadata-Version: 2.4
Name: tools4all
Version: 0.2.4
Summary: Function calling capabilities for LLMs that don't natively support them
Home-page: https://github.com/alfredwallace7/tools4all
Author: Alfred Wallace
Author-email: Alfred Wallace <alfred.wallace@netcraft.fr>
License: MIT
Project-URL: Homepage, https://github.com/alfredwallace7/tools4all
Project-URL: Issues, https://github.com/alfredwallace7/tools4all/issues
Classifier: Programming Language :: Python :: 3
Classifier: License :: OSI Approved :: MIT License
Classifier: Operating System :: OS Independent
Classifier: Development Status :: 4 - Beta
Classifier: Intended Audience :: Developers
Classifier: Topic :: Scientific/Engineering :: Artificial Intelligence
Requires-Python: >=3.8
License-File: LICENSE
Requires-Dist: ollama>=0.1.20
Requires-Dist: pydantic>=2.5.0
Requires-Dist: rich>=13.6.0
Dynamic: author
Dynamic: home-page
Dynamic: license-file
Dynamic: requires-python
